COPYING
MANIFEST.in
Readme.rst
setup.py
redditcurl/__init__.py
redditcurl/__main__.py
redditcurl/exceptions.py
redditcurl/manager.py
redditcurl.egg-info/PKG-INFO
redditcurl.egg-info/SOURCES.txt
redditcurl.egg-info/dependency_links.txt
redditcurl.egg-info/entry_points.txt
redditcurl.egg-info/requires.txt
redditcurl.egg-info/top_level.txt
redditcurl/websites/__init__.py
redditcurl/websites/deviantart.py
redditcurl/websites/direct.py
redditcurl/websites/gfycat.py
redditcurl/websites/imgur_album.py
redditcurl/websites/imgur_gifv.py
redditcurl/websites/imgur_link.py
redditcurl/websites/redditbooru_gallery.py
redditcurl/websites/shared_config.py
redditcurl/websites/twitter.py