Metadata-Version: 1.1
Name: redditcurl
Version: 2.1.0
Summary: Download the images you saved on Reddit.
Home-page: https://github.com/SeriousBug/redditcurl
Author: Kaan Genç
Author-email: pypi@kaangenc.me
License: GPLv3
Download-URL: https://github.com/SeriousBug/redditcurl/releases
Keywords: reddit,images,download
Platform: UNKNOWN
Classifier: Development Status :: 5 - Production/Stable
Classifier: Environment :: Console
Classifier: License :: OSI Approved :: GNU General Public License v3 or later (GPLv3+)
Classifier: Natural Language :: English
Classifier: Programming Language :: Python :: 3 :: Only
Classifier: Topic :: Software Development :: Libraries
Classifier: Topic :: Utilities
